diffdigest/__init__.py
diffdigest/cli.py
diffdigest-0.1.0.dist-info/entry_points.txt
diffdigest-0.1.0.dist-info/WHEEL
diffdigest-0.1.0.dist-info/METADATA
diffdigest-0.1.0.dist-info/RECORD
